setup.cfg
setup.py
src/taras/__init__.py
src/taras.python26.egg-info/PKG-INFO
src/taras.python26.egg-info/SOURCES.txt
src/taras.python26.egg-info/dependency_links.txt
src/taras.python26.egg-info/entry_points.txt
src/taras.python26.egg-info/namespace_packages.txt
src/taras.python26.egg-info/not-zip-safe
src/taras.python26.egg-info/paster_plugins.txt
src/taras.python26.egg-info/top_level.txt
src/taras/python26/__init__.py
src/taras/python26/subprocess.py