Metadata-Version: 1.0
Name: taras.python26
Version: 0.1final
Summary: Collection of useful functions from python2.6 that can be used in python 2.5. Namely: subprocess
Home-page: http://github.com/taras/taras.python26
Author: Taras Mankovski
Author-email: tarasm@gmail.com
License: GPL
Keywords: python2.6 subprocess
Platform: UNKNOWN
